[
  {
    "framework": "actix",
    "language": "Rust",
    "rps": 2309690,
    "avg_latency": "139us",
    "p99_latency": "330us",
    "cpu": "6075.6%",
    "memory": "54.8MiB",
    "connections": 512,
    "threads": 64,
    "duration": "5s",
    "pipeline": 1,
    "bandwidth": "273.19MB/s",
    "input_bw": "178.42MB/s",
    "reconnects": 51,
    "status_2xx": 11548454,
    "status_3xx": 0,
    "status_4xx": 0,
    "status_5xx": 0,
    "type": "production"
  },
  {
    "framework": "aspnet-minimal",
    "language": "C#",
    "rps": 541070,
    "avg_latency": "946us",
    "p99_latency": "2.49ms",
    "cpu": "3585.5%",
    "memory": "219.7MiB",
    "connections": 512,
    "threads": 64,
    "duration": "5s",
    "pipeline": 1,
    "bandwidth": "86.14MB/s",
    "input_bw": "41.80MB/s",
    "reconnects": 0,
    "status_2xx": 2705352,
    "status_3xx": 0,
    "status_4xx": 0,
    "status_5xx": 0,
    "type": "production"
  },
  {
    "framework": "aspnet-mvc",
    "language": "C#",
    "rps": 207939,
    "avg_latency": "2.47ms",
    "p99_latency": "6.78ms",
    "cpu": "3212.9%",
    "memory": "196.4MiB",
    "connections": 512,
    "threads": 64,
    "duration": "5s",
    "pipeline": 1,
    "bandwidth": "33.10MB/s",
    "input_bw": "16.06MB/s",
    "reconnects": 0,
    "status_2xx": 1039699,
    "status_3xx": 0,
    "status_4xx": 0,
    "status_5xx": 0,
    "type": "production"
  },
  {
    "framework": "blitz",
    "language": "Zig",
    "rps": 2587281,
    "avg_latency": "197us",
    "p99_latency": "1.20ms",
    "cpu": "6381.4%",
    "memory": "4.4GiB",
    "connections": 512,
    "threads": 64,
    "duration": "5s",
    "pipeline": 1,
    "bandwidth": "199.72MB/s",
    "input_bw": "199.86MB/s",
    "reconnects": 0,
    "status_2xx": 12936408,
    "status_3xx": 0,
    "status_4xx": 0,
    "status_5xx": 0,
    "type": "engine"
  },
  {
    "framework": "bun",
    "language": "TS",
    "rps": 1694299,
    "avg_latency": "301us",
    "p99_latency": "1.25ms",
    "cpu": "6501.6%",
    "memory": "1.4GiB",
    "connections": 512,
    "threads": 64,
    "duration": "5s",
    "pipeline": 1,
    "bandwidth": "166.38MB/s",
    "input_bw": "130.88MB/s",
    "reconnects": 0,
    "status_2xx": 8471497,
    "status_3xx": 0,
    "status_4xx": 0,
    "status_5xx": 0,
    "type": "engine"
  },
  {
    "framework": "caddy",
    "language": "Go",
    "rps": 583259,
    "avg_latency": "878us",
    "p99_latency": "8.66ms",
    "cpu": "5284.7%",
    "memory": "194.8MiB",
    "connections": 512,
    "threads": 64,
    "duration": "5s",
    "pipeline": 1,
    "bandwidth": "65.62MB/s",
    "input_bw": "45.06MB/s",
    "reconnects": 0,
    "status_2xx": 2916298,
    "status_3xx": 0,
    "status_4xx": 0,
    "status_5xx": 0,
    "type": "engine"
  },
  {
    "framework": "carno",
    "language": "TS",
    "rps": 1272274,
    "avg_latency": "401us",
    "p99_latency": "2.94ms",
    "cpu": "6591.0%",
    "memory": "3.3GiB",
    "connections": 512,
    "threads": 64,
    "duration": "5s",
    "pipeline": 1,
    "bandwidth": "124.89MB/s",
    "input_bw": "98.28MB/s",
    "reconnects": 0,
    "status_2xx": 6361370,
    "status_3xx": 0,
    "status_4xx": 0,
    "status_5xx": 0,
    "type": "production"
  },
  {
    "framework": "chi",
    "language": "Go",
    "rps": 271586,
    "avg_latency": "1.89ms",
    "p99_latency": "14.30ms",
    "cpu": "4510.1%",
    "memory": "141.8MiB",
    "connections": 512,
    "threads": 64,
    "duration": "5s",
    "pipeline": 1,
    "bandwidth": "33.92MB/s",
    "input_bw": "20.98MB/s",
    "reconnects": 0,
    "status_2xx": 1357931,
    "status_3xx": 0,
    "status_4xx": 0,
    "status_5xx": 0,
    "type": "tuned"
  },
  {
    "framework": "deno",
    "language": "TS",
    "rps": 1313857,
    "avg_latency": "389us",
    "p99_latency": "1.00ms",
    "cpu": "6493.4%",
    "memory": "9.2GiB",
    "connections": 512,
    "threads": 64,
    "duration": "5s",
    "pipeline": 1,
    "bandwidth": "175.38MB/s",
    "input_bw": "101.49MB/s",
    "reconnects": 0,
    "status_2xx": 6569288,
    "status_3xx": 0,
    "status_4xx": 0,
    "status_5xx": 0,
    "type": "production"
  },
  {
    "framework": "django",
    "language": "Python",
    "rps": 106243,
    "avg_latency": "4.63ms",
    "p99_latency": "17.60ms",
    "cpu": "5476.0%",
    "memory": "3.9GiB",
    "connections": 512,
    "threads": 64,
    "duration": "5s",
    "pipeline": 1,
    "bandwidth": "16.10MB/s",
    "input_bw": "8.21MB/s",
    "reconnects": 531217,
    "status_2xx": 531218,
    "status_3xx": 0,
    "status_4xx": 0,
    "status_5xx": 0,
    "type": "tuned"
  },
  {
    "framework": "echo",
    "language": "Go",
    "rps": 281236,
    "avg_latency": "1.82ms",
    "p99_latency": "13.80ms",
    "cpu": "4426.0%",
    "memory": "128.0MiB",
    "connections": 512,
    "threads": 64,
    "duration": "5s",
    "pipeline": 1,
    "bandwidth": "35.39MB/s",
    "input_bw": "21.72MB/s",
    "reconnects": 0,
    "status_2xx": 1406183,
    "status_3xx": 0,
    "status_4xx": 0,
    "status_5xx": 0,
    "type": "tuned"
  },
  {
    "framework": "elysia",
    "language": "TS",
    "rps": 1224202,
    "avg_latency": "417us",
    "p99_latency": "3.38ms",
    "cpu": "6557.4%",
    "memory": "5.1GiB",
    "connections": 512,
    "threads": 64,
    "duration": "5s",
    "pipeline": 1,
    "bandwidth": "120.22MB/s",
    "input_bw": "94.57MB/s",
    "reconnects": 0,
    "status_2xx": 6121014,
    "status_3xx": 0,
    "status_4xx": 0,
    "status_5xx": 0,
    "type": "production"
  },
  {
    "framework": "express",
    "language": "JS",
    "rps": 284170,
    "avg_latency": "1.80ms",
    "p99_latency": "11.30ms",
    "cpu": "6521.1%",
    "memory": "5.5GiB",
    "connections": 512,
    "threads": 64,
    "duration": "5s",
    "pipeline": 1,
    "bandwidth": "66.64MB/s",
    "input_bw": "21.95MB/s",
    "reconnects": 0,
    "status_2xx": 1420852,
    "status_3xx": 0,
    "status_4xx": 0,
    "status_5xx": 0,
    "type": "tuned"
  },
  {
    "framework": "fastapi",
    "language": "Python",
    "rps": 273510,
    "avg_latency": "1.86ms",
    "p99_latency": "42.40ms",
    "cpu": "6373.5%",
    "memory": "8.4GiB",
    "connections": 512,
    "threads": 64,
    "duration": "5s",
    "pipeline": 1,
    "bandwidth": "39.63MB/s",
    "input_bw": "21.13MB/s",
    "reconnects": 0,
    "status_2xx": 1367550,
    "status_3xx": 0,
    "status_4xx": 0,
    "status_5xx": 0,
    "type": "tuned"
  },
  {
    "framework": "fastify",
    "language": "JS",
    "rps": 771017,
    "avg_latency": "664us",
    "p99_latency": "4.77ms",
    "cpu": "6518.9%",
    "memory": "5.9GiB",
    "connections": 512,
    "threads": 64,
    "duration": "5s",
    "pipeline": 1,
    "bandwidth": "123.48MB/s",
    "input_bw": "59.56MB/s",
    "reconnects": 0,
    "status_2xx": 3855088,
    "status_3xx": 0,
    "status_4xx": 0,
    "status_5xx": 0,
    "type": "tuned"
  },
  {
    "framework": "fastpysgi-asgi",
    "language": "Python",
    "rps": 594614,
    "avg_latency": "858us",
    "p99_latency": "5.19ms",
    "cpu": "6396.9%",
    "memory": "500.1MiB",
    "connections": 512,
    "threads": 64,
    "duration": "5s",
    "pipeline": 1,
    "bandwidth": "93.53MB/s",
    "input_bw": "45.93MB/s",
    "reconnects": 0,
    "status_2xx": 2973074,
    "status_3xx": 0,
    "status_4xx": 0,
    "status_5xx": 0,
    "type": "engine"
  },
  {
    "framework": "fastpysgi-wsgi",
    "language": "Python",
    "rps": 1301932,
    "avg_latency": "392us",
    "p99_latency": "2.00ms",
    "cpu": "6529.5%",
    "memory": "408.4MiB",
    "connections": 512,
    "threads": 64,
    "duration": "5s",
    "pipeline": 1,
    "bandwidth": "204.79MB/s",
    "input_bw": "100.57MB/s",
    "reconnects": 0,
    "status_2xx": 6509663,
    "status_3xx": 0,
    "status_4xx": 0,
    "status_5xx": 0,
    "type": "engine"
  },
  {
    "framework": "fiber",
    "language": "Go",
    "rps": 394387,
    "avg_latency": "1.30ms",
    "p99_latency": "13.20ms",
    "cpu": "2914.7%",
    "memory": "90.8MiB",
    "connections": 512,
    "threads": 64,
    "duration": "5s",
    "pipeline": 1,
    "bandwidth": "50.01MB/s",
    "input_bw": "30.47MB/s",
    "reconnects": 0,
    "status_2xx": 1971935,
    "status_3xx": 0,
    "status_4xx": 0,
    "status_5xx": 0,
    "type": "tuned"
  },
  {
    "framework": "flask",
    "language": "Python",
    "rps": 118426,
    "avg_latency": "4.16ms",
    "p99_latency": "6.95ms",
    "cpu": "5266.6%",
    "memory": "3.2GiB",
    "connections": 512,
    "threads": 64,
    "duration": "5s",
    "pipeline": 1,
    "bandwidth": "15.81MB/s",
    "input_bw": "9.15MB/s",
    "reconnects": 592134,
    "status_2xx": 592133,
    "status_3xx": 0,
    "status_4xx": 0,
    "status_5xx": 0,
    "type": "tuned"
  },
  {
    "framework": "fletch",
    "language": "Dart",
    "rps": 180487,
    "avg_latency": "2.31ms",
    "p99_latency": "3.85ms",
    "cpu": "1374.3%",
    "memory": "1.3GiB",
    "connections": 512,
    "threads": 64,
    "duration": "5s",
    "pipeline": 1,
    "bandwidth": "33.55MB/s",
    "input_bw": "13.94MB/s",
    "reconnects": 0,
    "status_2xx": 902437,
    "status_3xx": 0,
    "status_4xx": 0,
    "status_5xx": 0,
    "type": "tuned"
  },
  {
    "framework": "genhttp",
    "language": "C#",
    "rps": 48905,
    "avg_latency": "6.49ms",
    "p99_latency": "13.30ms",
    "cpu": "5154.0%",
    "memory": "241.5MiB",
    "connections": 512,
    "threads": 64,
    "duration": "5s",
    "pipeline": 1,
    "bandwidth": "6.29MB/s",
    "input_bw": "3.78MB/s",
    "reconnects": 0,
    "status_2xx": 244525,
    "status_3xx": 0,
    "status_4xx": 0,
    "status_5xx": 0,
    "type": "production"
  },
  {
    "framework": "gin",
    "language": "Go",
    "rps": 291741,
    "avg_latency": "1.76ms",
    "p99_latency": "13.00ms",
    "cpu": "4395.7%",
    "memory": "122.2MiB",
    "connections": 512,
    "threads": 64,
    "duration": "5s",
    "pipeline": 1,
    "bandwidth": "36.44MB/s",
    "input_bw": "22.54MB/s",
    "reconnects": 0,
    "status_2xx": 1458708,
    "status_3xx": 0,
    "status_4xx": 0,
    "status_5xx": 0,
    "type": "tuned"
  },
  {
    "framework": "go-fasthttp",
    "language": "Go",
    "rps": 1200022,
    "avg_latency": "429us",
    "p99_latency": "1.96ms",
    "cpu": "6287.5%",
    "memory": "74.2MiB",
    "connections": 512,
    "threads": 64,
    "duration": "5s",
    "pipeline": 1,
    "bandwidth": "141.81MB/s",
    "input_bw": "92.70MB/s",
    "reconnects": 0,
    "status_2xx": 6000110,
    "status_3xx": 0,
    "status_4xx": 0,
    "status_5xx": 0,
    "type": "production"
  },
  {
    "framework": "h2o",
    "language": "C",
    "rps": 2669601,
    "avg_latency": "191us",
    "p99_latency": "1.38ms",
    "cpu": "6538.9%",
    "memory": "69.1MiB",
    "connections": 512,
    "threads": 64,
    "duration": "5s",
    "pipeline": 1,
    "bandwidth": "262.27MB/s",
    "input_bw": "206.22MB/s",
    "reconnects": 0,
    "status_2xx": 13374702,
    "status_3xx": 0,
    "status_4xx": 0,
    "status_5xx": 0,
    "type": "engine"
  },
  {
    "framework": "h2o-mruby",
    "language": "Ruby",
    "rps": 1420425,
    "avg_latency": "360us",
    "p99_latency": "1.97ms",
    "cpu": "6553.3%",
    "memory": "262.8MiB",
    "connections": 512,
    "threads": 64,
    "duration": "5s",
    "pipeline": 1,
    "bandwidth": "213.97MB/s",
    "input_bw": "109.72MB/s",
    "reconnects": 0,
    "status_2xx": 7102126,
    "status_3xx": 0,
    "status_4xx": 0,
    "status_5xx": 0,
    "type": "tuned"
  },
  {
    "framework": "helidon",
    "language": "Java",
    "rps": 18128,
    "avg_latency": "28.29ms",
    "p99_latency": "83.20ms",
    "cpu": "323.2%",
    "memory": "8.5GiB",
    "connections": 512,
    "threads": 64,
    "duration": "5s",
    "pipeline": 1,
    "bandwidth": "2.49MB/s",
    "input_bw": "1.40MB/s",
    "reconnects": 0,
    "status_2xx": 90642,
    "status_3xx": 0,
    "status_4xx": 0,
    "status_5xx": 0,
    "type": "tuned"
  },
  {
    "framework": "hono-bun",
    "language": "TS",
    "rps": 1108947,
    "avg_latency": "460us",
    "p99_latency": "3.97ms",
    "cpu": "6479.9%",
    "memory": "3.4GiB",
    "connections": 512,
    "threads": 64,
    "duration": "5s",
    "pipeline": 1,
    "bandwidth": "127.92MB/s",
    "input_bw": "85.66MB/s",
    "reconnects": 0,
    "status_2xx": 5544735,
    "status_3xx": 0,
    "status_4xx": 0,
    "status_5xx": 0,
    "type": "production"
  },
  {
    "framework": "hono",
    "language": "JS",
    "rps": 552997,
    "avg_latency": "924us",
    "p99_latency": "3.04ms",
    "cpu": "6524.3%",
    "memory": "8.5GiB",
    "connections": 512,
    "threads": 64,
    "duration": "5s",
    "pipeline": 1,
    "bandwidth": "94.36MB/s",
    "input_bw": "42.72MB/s",
    "reconnects": 0,
    "status_2xx": 2764985,
    "status_3xx": 0,
    "status_4xx": 0,
    "status_5xx": 0,
    "type": "tuned"
  },
  {
    "framework": "humming-bird",
    "language": "Swift",
    "rps": 303336,
    "avg_latency": "1.58ms",
    "p99_latency": "25.80ms",
    "cpu": "6459.8%",
    "memory": "83.0MiB",
    "connections": 512,
    "threads": 64,
    "duration": "5s",
    "pipeline": 1,
    "bandwidth": "35.86MB/s",
    "input_bw": "23.43MB/s",
    "reconnects": 0,
    "status_2xx": 1516681,
    "status_3xx": 0,
    "status_4xx": 0,
    "status_5xx": 0,
    "type": "tuned"
  },
  {
    "framework": "hyper",
    "language": "Rust",
    "rps": 2696983,
    "avg_latency": "189us",
    "p99_latency": "531us",
    "cpu": "6252.2%",
    "memory": "41.3MiB",
    "connections": 512,
    "threads": 64,
    "duration": "5s",
    "pipeline": 1,
    "bandwidth": "303.36MB/s",
    "input_bw": "208.34MB/s",
    "reconnects": 0,
    "status_2xx": 13484915,
    "status_3xx": 0,
    "status_4xx": 0,
    "status_5xx": 0,
    "type": "engine"
  },
  {
    "framework": "koa",
    "language": "JS",
    "rps": 815867,
    "avg_latency": "626us",
    "p99_latency": "1.47ms",
    "cpu": "6605.9%",
    "memory": "2.6GiB",
    "connections": 512,
    "threads": 64,
    "duration": "5s",
    "pipeline": 1,
    "bandwidth": "138.45MB/s",
    "input_bw": "63.02MB/s",
    "reconnects": 0,
    "status_2xx": 4079338,
    "status_3xx": 0,
    "status_4xx": 0,
    "status_5xx": 0,
    "type": "tuned"
  },
  {
    "framework": "ktor",
    "language": "Kotlin",
    "rps": 262626,
    "avg_latency": "1.95ms",
    "p99_latency": "19.90ms",
    "cpu": "6538.9%",
    "memory": "2.5GiB",
    "connections": 512,
    "threads": 64,
    "duration": "5s",
    "pipeline": 1,
    "bandwidth": "33.05MB/s",
    "input_bw": "20.29MB/s",
    "reconnects": 0,
    "status_2xx": 1313131,
    "status_3xx": 0,
    "status_4xx": 0,
    "status_5xx": 0,
    "type": "tuned"
  },
  {
    "framework": "may-minihttp",
    "language": "Rust",
    "rps": 2892251,
    "avg_latency": "176us",
    "p99_latency": "527us",
    "cpu": "6210.7%",
    "memory": "113.2MiB",
    "connections": 512,
    "threads": 64,
    "duration": "5s",
    "pipeline": 1,
    "bandwidth": "181.99MB/s",
    "input_bw": "223.42MB/s",
    "reconnects": 0,
    "status_2xx": 14461255,
    "status_3xx": 0,
    "status_4xx": 0,
    "status_5xx": 0,
    "type": "engine"
  },
  {
    "framework": "nginx",
    "language": "C",
    "rps": 2518385,
    "avg_latency": "202us",
    "p99_latency": "1.57ms",
    "cpu": "6326.5%",
    "memory": "3.5GiB",
    "connections": 512,
    "threads": 64,
    "duration": "5s",
    "pipeline": 1,
    "bandwidth": "340.86MB/s",
    "input_bw": "194.54MB/s",
    "reconnects": 0,
    "status_2xx": 12591926,
    "status_3xx": 0,
    "status_4xx": 0,
    "status_5xx": 0,
    "type": "engine"
  },
  {
    "framework": "nginx-openresty",
    "language": "Lua",
    "rps": 918595,
    "avg_latency": "556us",
    "p99_latency": "3.09ms",
    "cpu": "6439.5%",
    "memory": "4.0GiB",
    "connections": 512,
    "threads": 64,
    "duration": "5s",
    "pipeline": 1,
    "bandwidth": "144.49MB/s",
    "input_bw": "70.96MB/s",
    "reconnects": 0,
    "status_2xx": 4592978,
    "status_3xx": 0,
    "status_4xx": 0,
    "status_5xx": 0,
    "type": "tuned"
  },
  {
    "framework": "ngx-php",
    "language": "PHP",
    "rps": 2109756,
    "avg_latency": "246us",
    "p99_latency": "1.93ms",
    "cpu": "6353.1%",
    "memory": "6.3GiB",
    "connections": 512,
    "threads": 64,
    "duration": "5s",
    "pipeline": 1,
    "bandwidth": "285.42MB/s",
    "input_bw": "162.97MB/s",
    "reconnects": 0,
    "status_2xx": 10548780,
    "status_3xx": 0,
    "status_4xx": 0,
    "status_5xx": 0,
    "type": "tuned"
  },
  {
    "framework": "node",
    "language": "JS",
    "rps": 1175237,
    "avg_latency": "435us",
    "p99_latency": "995us",
    "cpu": "6562.3%",
    "memory": "2.0GiB",
    "connections": 512,
    "threads": 64,
    "duration": "5s",
    "pipeline": 1,
    "bandwidth": "179.27MB/s",
    "input_bw": "90.78MB/s",
    "reconnects": 0,
    "status_2xx": 5876185,
    "status_3xx": 0,
    "status_4xx": 0,
    "status_5xx": 0,
    "type": "engine"
  },
  {
    "framework": "ntex-tokio",
    "language": "Rust",
    "rps": 2669249,
    "avg_latency": "191us",
    "p99_latency": "356us",
    "cpu": "6429.9%",
    "memory": "53.2MiB",
    "connections": 512,
    "threads": 64,
    "duration": "5s",
    "pipeline": 1,
    "bandwidth": "297.76MB/s",
    "input_bw": "206.19MB/s",
    "reconnects": 0,
    "status_2xx": 13346245,
    "status_3xx": 0,
    "status_4xx": 0,
    "status_5xx": 0,
    "type": "production"
  },
  {
    "framework": "phoenix",
    "language": "Elixir",
    "rps": 309330,
    "avg_latency": "1.65ms",
    "p99_latency": "3.18ms",
    "cpu": "6501.9%",
    "memory": "335.3MiB",
    "connections": 512,
    "threads": 64,
    "duration": "5s",
    "pipeline": 1,
    "bandwidth": "50.73MB/s",
    "input_bw": "23.90MB/s",
    "reconnects": 1504,
    "status_2xx": 1546654,
    "status_3xx": 0,
    "status_4xx": 0,
    "status_5xx": 0,
    "type": "tuned"
  },
  {
    "framework": "quarkus-jvm",
    "language": "Java",
    "rps": 1768367,
    "avg_latency": "289us",
    "p99_latency": "559us",
    "cpu": "6693.1%",
    "memory": "4.4GiB",
    "connections": 512,
    "threads": 64,
    "duration": "5s",
    "pipeline": 1,
    "bandwidth": "170.28MB/s",
    "input_bw": "136.60MB/s",
    "reconnects": 0,
    "status_2xx": 8841839,
    "status_3xx": 0,
    "status_4xx": 0,
    "status_5xx": 0,
    "type": "tuned"
  },
  {
    "framework": "rage",
    "language": "Ruby",
    "rps": 346282,
    "avg_latency": "1.48ms",
    "p99_latency": "20.30ms",
    "cpu": "5996.0%",
    "memory": "5.1GiB",
    "connections": 512,
    "threads": 64,
    "duration": "5s",
    "pipeline": 1,
    "bandwidth": "49.85MB/s",
    "input_bw": "26.75MB/s",
    "reconnects": 0,
    "status_2xx": 1731410,
    "status_3xx": 0,
    "status_4xx": 0,
    "status_5xx": 0,
    "type": "tuned"
  },
  {
    "framework": "rails",
    "language": "Ruby",
    "rps": 56470,
    "avg_latency": "9.06ms",
    "p99_latency": "48.80ms",
    "cpu": "6528.0%",
    "memory": "8.5GiB",
    "connections": 512,
    "threads": 64,
    "duration": "5s",
    "pipeline": 1,
    "bandwidth": "11.47MB/s",
    "input_bw": "4.36MB/s",
    "reconnects": 152,
    "status_2xx": 282352,
    "status_3xx": 0,
    "status_4xx": 0,
    "status_5xx": 0,
    "type": "tuned"
  },
  {
    "framework": "ringzero",
    "language": "C",
    "rps": 3467377,
    "avg_latency": "147us",
    "p99_latency": "198us",
    "cpu": "6220.8%",
    "memory": "4.1GiB",
    "connections": 512,
    "threads": 64,
    "duration": "5s",
    "pipeline": 1,
    "bandwidth": "277.59MB/s",
    "input_bw": "267.85MB/s",
    "reconnects": 0,
    "status_2xx": 17336887,
    "status_3xx": 0,
    "status_4xx": 487,
    "status_5xx": 0,
    "type": "engine"
  },
  {
    "framework": "roda",
    "language": "Ruby",
    "rps": 81748,
    "avg_latency": "6.27ms",
    "p99_latency": "52.50ms",
    "cpu": "6498.3%",
    "memory": "7.4GiB",
    "connections": 512,
    "threads": 64,
    "duration": "5s",
    "pipeline": 1,
    "bandwidth": "6.24MB/s",
    "input_bw": "6.31MB/s",
    "reconnects": 298,
    "status_2xx": 408740,
    "status_3xx": 0,
    "status_4xx": 0,
    "status_5xx": 0,
    "type": "tuned"
  },
  {
    "framework": "rust-epoll",
    "language": "Rust",
    "rps": 3100381,
    "avg_latency": "164us",
    "p99_latency": "840us",
    "cpu": "5414.7%",
    "memory": "49.8MiB",
    "connections": 512,
    "threads": 64,
    "duration": "5s",
    "pipeline": 1,
    "bandwidth": "254.19MB/s",
    "input_bw": "239.50MB/s",
    "reconnects": 0,
    "status_2xx": 15501906,
    "status_3xx": 0,
    "status_4xx": 0,
    "status_5xx": 0,
    "type": "engine"
  },
  {
    "framework": "servicestack",
    "language": "C#",
    "rps": 13292,
    "avg_latency": "38.56ms",
    "p99_latency": "109.30ms",
    "cpu": "1666.3%",
    "memory": "365.9MiB",
    "connections": 512,
    "threads": 64,
    "duration": "5s",
    "pipeline": 1,
    "bandwidth": "2.67MB/s",
    "input_bw": "1.03MB/s",
    "reconnects": 0,
    "status_2xx": 66460,
    "status_3xx": 0,
    "status_4xx": 0,
    "status_5xx": 0,
    "type": "tuned"
  },
  {
    "framework": "simplew",
    "language": "C#",
    "rps": 1061703,
    "avg_latency": "481us",
    "p99_latency": "2.78ms",
    "cpu": "4943.6%",
    "memory": "217.5MiB",
    "connections": 512,
    "threads": 64,
    "duration": "5s",
    "pipeline": 1,
    "bandwidth": "149.80MB/s",
    "input_bw": "82.01MB/s",
    "reconnects": 0,
    "status_2xx": 5308519,
    "status_3xx": 0,
    "status_4xx": 0,
    "status_5xx": 0,
    "type": "tuned"
  },
  {
    "framework": "sinatra",
    "language": "Ruby",
    "rps": 80878,
    "avg_latency": "6.32ms",
    "p99_latency": "57.30ms",
    "cpu": "6445.0%",
    "memory": "8.4GiB",
    "connections": 512,
    "threads": 64,
    "duration": "5s",
    "pipeline": 1,
    "bandwidth": "7.48MB/s",
    "input_bw": "6.25MB/s",
    "reconnects": 321,
    "status_2xx": 404391,
    "status_3xx": 0,
    "status_4xx": 0,
    "status_5xx": 0,
    "type": "tuned"
  },
  {
    "framework": "sisk",
    "language": "C#",
    "rps": 113335,
    "avg_latency": "4.49ms",
    "p99_latency": "12.80ms",
    "cpu": "3990.4%",
    "memory": "209.1MiB",
    "connections": 512,
    "threads": 64,
    "duration": "5s",
    "pipeline": 1,
    "bandwidth": "14.26MB/s",
    "input_bw": "8.75MB/s",
    "reconnects": 0,
    "status_2xx": 566676,
    "status_3xx": 0,
    "status_4xx": 0,
    "status_5xx": 0,
    "type": "tuned"
  },
  {
    "framework": "spring-jvm",
    "language": "Java",
    "rps": 262511,
    "avg_latency": "1.95ms",
    "p99_latency": "4.08ms",
    "cpu": "2210.6%",
    "memory": "2.0GiB",
    "connections": 512,
    "threads": 64,
    "duration": "5s",
    "pipeline": 1,
    "bandwidth": "33.83MB/s",
    "input_bw": "20.28MB/s",
    "reconnects": 12952,
    "status_2xx": 1312555,
    "status_3xx": 0,
    "status_4xx": 0,
    "status_5xx": 0,
    "type": "tuned"
  },
  {
    "framework": "starlette",
    "language": "Python",
    "rps": 344390,
    "avg_latency": "1.49ms",
    "p99_latency": "40.50ms",
    "cpu": "6411.7%",
    "memory": "4.7GiB",
    "connections": 512,
    "threads": 64,
    "duration": "5s",
    "pipeline": 1,
    "bandwidth": "50.56MB/s",
    "input_bw": "26.60MB/s",
    "reconnects": 0,
    "status_2xx": 1721950,
    "status_3xx": 0,
    "status_4xx": 0,
    "status_5xx": 0,
    "type": "tuned"
  },
  {
    "framework": "ultimate-express",
    "language": "JS",
    "rps": 1369003,
    "avg_latency": "373us",
    "p99_latency": "989us",
    "cpu": "6704.7%",
    "memory": "2.5GiB",
    "connections": 512,
    "threads": 64,
    "duration": "5s",
    "pipeline": 1,
    "bandwidth": "250.58MB/s",
    "input_bw": "105.75MB/s",
    "reconnects": 0,
    "status_2xx": 6845016,
    "status_3xx": 0,
    "status_4xx": 0,
    "status_5xx": 0,
    "type": "tuned"
  },
  {
    "framework": "uwebsockets",
    "language": "JS",
    "rps": 2307758,
    "avg_latency": "221us",
    "p99_latency": "608us",
    "cpu": "6578.0%",
    "memory": "834.1MiB",
    "connections": 512,
    "threads": 64,
    "duration": "5s",
    "pipeline": 1,
    "bandwidth": "310.22MB/s",
    "input_bw": "178.27MB/s",
    "reconnects": 0,
    "status_2xx": 11538791,
    "status_3xx": 0,
    "status_4xx": 0,
    "status_5xx": 0,
    "type": "engine"
  },
  {
    "framework": "vertx",
    "language": "Java",
    "rps": 2073940,
    "avg_latency": "246us",
    "p99_latency": "516us",
    "cpu": "6409.2%",
    "memory": "10.5GiB",
    "connections": 512,
    "threads": 64,
    "duration": "5s",
    "pipeline": 1,
    "bandwidth": "130.49MB/s",
    "input_bw": "160.21MB/s",
    "reconnects": 0,
    "status_2xx": 10369700,
    "status_3xx": 0,
    "status_4xx": 0,
    "status_5xx": 0,
    "type": "engine"
  },
  {
    "framework": "workerman",
    "language": "PHP",
    "rps": 2455148,
    "avg_latency": "208us",
    "p99_latency": "1.69ms",
    "cpu": "6461.3%",
    "memory": "1.8GiB",
    "connections": 512,
    "threads": 64,
    "duration": "5s",
    "pipeline": 1,
    "bandwidth": "210.54MB/s",
    "input_bw": "189.65MB/s",
    "reconnects": 0,
    "status_2xx": 12275741,
    "status_3xx": 0,
    "status_4xx": 0,
    "status_5xx": 0,
    "type": "tuned"
  }
]