[
  {
    "framework": "actix-websocket",
    "language": "Rust",
    "rps": 3456617,
    "avg_latency": "1.03ms",
    "p99_latency": "1.92ms",
    "cpu": "6306.9%",
    "memory": "202.0MiB",
    "connections": 4096,
    "threads": 64,
    "duration": "5s",
    "pipeline": 1,
    "bandwidth": "23.19MB/s",
    "input_bw": "",
    "reconnects": 0,
    "status_2xx": 17283088,
    "status_3xx": 0,
    "status_4xx": 0,
    "status_5xx": 0
  },
  {
    "framework": "aspnet-websocket",
    "language": "C#",
    "rps": 1863478,
    "avg_latency": "1.63ms",
    "p99_latency": "4.50ms",
    "cpu": "6298.6%",
    "memory": "385.6MiB",
    "connections": 4096,
    "threads": 64,
    "duration": "5s",
    "pipeline": 1,
    "bandwidth": "12.55MB/s",
    "input_bw": "",
    "reconnects": 0,
    "status_2xx": 9317390,
    "status_3xx": 0,
    "status_4xx": 0,
    "status_5xx": 0
  },
  {
    "framework": "bun-websocket",
    "language": "TS",
    "rps": 3847529,
    "avg_latency": "1.06ms",
    "p99_latency": "2.39ms",
    "cpu": "6120.1%",
    "memory": "613.7MiB",
    "connections": 4096,
    "threads": 64,
    "duration": "5s",
    "pipeline": 1,
    "bandwidth": "25.73MB/s",
    "input_bw": "",
    "reconnects": 0,
    "status_2xx": 19237649,
    "status_3xx": 0,
    "status_4xx": 0,
    "status_5xx": 0
  },
  {
    "framework": "deno-websocket",
    "language": "TS",
    "rps": 2741635,
    "avg_latency": "1.47ms",
    "p99_latency": "2.36ms",
    "cpu": "6384.3%",
    "memory": "3.8GiB",
    "connections": 4096,
    "threads": 64,
    "duration": "5s",
    "pipeline": 1,
    "bandwidth": "18.42MB/s",
    "input_bw": "",
    "reconnects": 0,
    "status_2xx": 13708175,
    "status_3xx": 0,
    "status_4xx": 0,
    "status_5xx": 0
  },
  {
    "framework": "genhttp",
    "language": "C#",
    "rps": 2238063,
    "avg_latency": "1.59ms",
    "p99_latency": "4.68ms",
    "cpu": "5998.4%",
    "memory": "496.6MiB",
    "connections": 4096,
    "threads": 64,
    "duration": "5s",
    "pipeline": 1,
    "bandwidth": "15.05MB/s",
    "input_bw": "",
    "reconnects": 0,
    "status_2xx": 11190315,
    "status_3xx": 0,
    "status_4xx": 0,
    "status_5xx": 0
  },
  {
    "framework": "go-websocket",
    "language": "Go",
    "rps": 1076993,
    "avg_latency": "3.44ms",
    "p99_latency": "38.20ms",
    "cpu": "5608.6%",
    "memory": "192.2MiB",
    "connections": 4096,
    "threads": 64,
    "duration": "5s",
    "pipeline": 1,
    "bandwidth": "7.28MB/s",
    "input_bw": "",
    "reconnects": 0,
    "status_2xx": 5384967,
    "status_3xx": 0,
    "status_4xx": 0,
    "status_5xx": 0
  },
  {
    "framework": "node-websocket",
    "language": "JS",
    "rps": 2030280,
    "avg_latency": "1.31ms",
    "p99_latency": "2.62ms",
    "cpu": "6463.8%",
    "memory": "1.4GiB",
    "connections": 4096,
    "threads": 64,
    "duration": "5s",
    "pipeline": 1,
    "bandwidth": "13.64MB/s",
    "input_bw": "",
    "reconnects": 0,
    "status_2xx": 10151400,
    "status_3xx": 0,
    "status_4xx": 0,
    "status_5xx": 0
  },
  {
    "framework": "simplew",
    "language": "C#",
    "rps": 1857405,
    "avg_latency": "2.10ms",
    "p99_latency": "5.68ms",
    "cpu": "5878.3%",
    "memory": "706.8MiB",
    "connections": 4096,
    "threads": 64,
    "duration": "5s",
    "pipeline": 1,
    "bandwidth": "12.51MB/s",
    "input_bw": "",
    "reconnects": 0,
    "status_2xx": 9287029,
    "status_3xx": 0,
    "status_4xx": 0,
    "status_5xx": 0
  },
  {
    "framework": "spring-boot",
    "language": "Java",
    "rps": 294492,
    "avg_latency": "5.97ms",
    "p99_latency": "13.50ms",
    "cpu": "827.3%",
    "memory": "1.3GiB",
    "connections": 4096,
    "threads": 64,
    "duration": "5s",
    "pipeline": 1,
    "bandwidth": "2.04MB/s",
    "input_bw": "",
    "reconnects": 0,
    "status_2xx": 1472463,
    "status_3xx": 0,
    "status_4xx": 0,
    "status_5xx": 0
  },
  {
    "framework": "Swoole",
    "language": "PHP",
    "rps": 3409498,
    "avg_latency": "1.20ms",
    "p99_latency": "6.86ms",
    "cpu": "6348.9%",
    "memory": "195.1MiB",
    "connections": 4096,
    "threads": 64,
    "duration": "5s",
    "pipeline": 1,
    "bandwidth": "22.90MB/s",
    "input_bw": "",
    "reconnects": 0,
    "status_2xx": 17047492,
    "status_3xx": 0,
    "status_4xx": 0,
    "status_5xx": 0
  },
  {
    "framework": "workerman-websocket",
    "language": "PHP",
    "rps": 3484682,
    "avg_latency": "1.17ms",
    "p99_latency": "2.50ms",
    "cpu": "6272.2%",
    "memory": "152.9MiB",
    "connections": 4096,
    "threads": 64,
    "duration": "5s",
    "pipeline": 1,
    "bandwidth": "23.29MB/s",
    "input_bw": "",
    "reconnects": 0,
    "status_2xx": 17423414,
    "status_3xx": 0,
    "status_4xx": 0,
    "status_5xx": 0
  }
]