[
  {
    "framework": "actix",
    "language": "Rust",
    "rps": 3424767,
    "avg_latency": "1.03ms",
    "p99_latency": "1.97ms",
    "cpu": "6276.4%",
    "memory": "200.2MiB",
    "connections": 4096,
    "threads": 64,
    "duration": "5s",
    "pipeline": 1,
    "bandwidth": "22.98MB/s",
    "input_bw": "",
    "reconnects": 0,
    "status_2xx": 17123837,
    "status_3xx": 0,
    "status_4xx": 0,
    "status_5xx": 0
  },
  {
    "framework": "aspnet-minimal",
    "language": "C#",
    "rps": 1806996,
    "avg_latency": "1.72ms",
    "p99_latency": "5.25ms",
    "cpu": "6120.1%",
    "memory": "389.2MiB",
    "connections": 4096,
    "threads": 64,
    "duration": "5s",
    "pipeline": 1,
    "bandwidth": "12.20MB/s",
    "reconnects": 0,
    "status_2xx": 9034981,
    "status_3xx": 0,
    "status_4xx": 0,
    "status_5xx": 0
  },
  {
    "framework": "bun-websocket",
    "language": "TS",
    "rps": 3793135,
    "avg_latency": "1.08ms",
    "p99_latency": "2.51ms",
    "cpu": "6321.3%",
    "memory": "633.5MiB",
    "connections": 4096,
    "threads": 64,
    "duration": "5s",
    "pipeline": 1,
    "bandwidth": "25.44MB/s",
    "input_bw": "",
    "reconnects": 0,
    "status_2xx": 18965678,
    "status_3xx": 0,
    "status_4xx": 0,
    "status_5xx": 0
  },
  {
    "framework": "deno-websocket",
    "language": "TS",
    "rps": 2718380,
    "avg_latency": "1.49ms",
    "p99_latency": "2.58ms",
    "cpu": "6373.7%",
    "memory": "3.7GiB",
    "connections": 4096,
    "threads": 64,
    "duration": "5s",
    "pipeline": 1,
    "bandwidth": "18.27MB/s",
    "input_bw": "",
    "reconnects": 0,
    "status_2xx": 13591900,
    "status_3xx": 0,
    "status_4xx": 0,
    "status_5xx": 0
  },
  {
    "framework": "go-websocket",
    "language": "Go",
    "rps": 1089321,
    "avg_latency": "3.43ms",
    "p99_latency": "37.10ms",
    "cpu": "5660.4%",
    "memory": "194.5MiB",
    "connections": 4096,
    "threads": 64,
    "duration": "5s",
    "pipeline": 1,
    "bandwidth": "7.37MB/s",
    "input_bw": "",
    "reconnects": 0,
    "status_2xx": 5446606,
    "status_3xx": 0,
    "status_4xx": 0,
    "status_5xx": 0
  },
  {
    "framework": "helidon-production",
    "language": "Java",
    "rps": 2177523,
    "avg_latency": "1.59ms",
    "p99_latency": "3.03ms",
    "cpu": "6370.9%",
    "memory": "1.6GiB",
    "connections": 4096,
    "threads": 64,
    "duration": "5s",
    "pipeline": 1,
    "bandwidth": "14.63MB/s",
    "input_bw": "",
    "reconnects": 0,
    "status_2xx": 10887618,
    "status_3xx": 0,
    "status_4xx": 0,
    "status_5xx": 0
  },
  {
    "framework": "helidon-tuned",
    "language": "Java",
    "rps": 2212682,
    "avg_latency": "1.84ms",
    "p99_latency": "3.09ms",
    "cpu": "6415.9%",
    "memory": "1.7GiB",
    "connections": 4096,
    "threads": 64,
    "duration": "5s",
    "pipeline": 1,
    "bandwidth": "14.84MB/s",
    "input_bw": "",
    "reconnects": 0,
    "status_2xx": 11063412,
    "status_3xx": 0,
    "status_4xx": 0,
    "status_5xx": 0
  },
  {
    "framework": "node-websocket",
    "language": "JS",
    "rps": 1996581,
    "avg_latency": "1.51ms",
    "p99_latency": "3.02ms",
    "cpu": "6422.5%",
    "memory": "1.4GiB",
    "connections": 4096,
    "threads": 64,
    "duration": "5s",
    "pipeline": 1,
    "bandwidth": "13.43MB/s",
    "input_bw": "",
    "reconnects": 0,
    "status_2xx": 9982908,
    "status_3xx": 0,
    "status_4xx": 0,
    "status_5xx": 0
  },
  {
    "framework": "Swoole",
    "language": "PHP",
    "rps": 3354954,
    "avg_latency": "1.22ms",
    "p99_latency": "6.79ms",
    "cpu": "6338.1%",
    "memory": "194.5MiB",
    "connections": 4096,
    "threads": 64,
    "duration": "5s",
    "pipeline": 1,
    "bandwidth": "22.56MB/s",
    "input_bw": "",
    "reconnects": 0,
    "status_2xx": 16774770,
    "status_3xx": 0,
    "status_4xx": 0,
    "status_5xx": 0
  },
  {
    "framework": "workerman-websocket",
    "language": "PHP",
    "rps": 3413565,
    "avg_latency": "1.20ms",
    "p99_latency": "2.54ms",
    "cpu": "6499.4%",
    "memory": "165.8MiB",
    "connections": 4096,
    "threads": 64,
    "duration": "5s",
    "pipeline": 1,
    "bandwidth": "22.81MB/s",
    "input_bw": "",
    "reconnects": 0,
    "status_2xx": 17067829,
    "status_3xx": 0,
    "status_4xx": 0,
    "status_5xx": 0
  }
]