[
  {
    "framework": "actix",
    "language": "Rust",
    "rps": 1195793,
    "avg_latency": "419us",
    "p99_latency": "3.80ms",
    "cpu": "4622.6%",
    "memory": "76MiB",
    "connections": 512,
    "threads": 64,
    "duration": "5s",
    "pipeline": 1,
    "bandwidth": "150.49MB/s",
    "reconnects": 597899,
    "status_2xx": 5978968,
    "status_3xx": 0,
    "status_4xx": 0,
    "status_5xx": 0
  },
  {
    "framework": "aleph",
    "language": "Clojure",
    "rps": 528420,
    "avg_latency": "958us",
    "p99_latency": "8.64ms",
    "cpu": "3508.5%",
    "memory": "8.8GiB",
    "connections": 512,
    "threads": 64,
    "duration": "5s",
    "pipeline": 1,
    "bandwidth": "79.10MB/s",
    "input_bw": "40.82MB/s",
    "reconnects": 264110,
    "status_2xx": 2642104,
    "status_3xx": 0,
    "status_4xx": 0,
    "status_5xx": 0
  },
  {
    "framework": "apache",
    "language": "C",
    "rps": 175981,
    "avg_latency": "2.87ms",
    "p99_latency": "11.80ms",
    "cpu": "5791.8%",
    "memory": "223MiB",
    "connections": 512,
    "threads": 64,
    "duration": "5s",
    "pipeline": 1,
    "bandwidth": "19.79MB/s",
    "reconnects": 108893,
    "status_2xx": 879906,
    "status_3xx": 0,
    "status_4xx": 0,
    "status_5xx": 0
  },
  {
    "framework": "aspnet-minimal",
    "language": "C#",
    "rps": 486117,
    "avg_latency": "1.03ms",
    "p99_latency": "11.30ms",
    "cpu": "3582.3%",
    "memory": "193.0MiB",
    "connections": 512,
    "threads": 64,
    "duration": "5s",
    "pipeline": 1,
    "bandwidth": "76.93MB/s",
    "reconnects": 243051,
    "status_2xx": 2430586,
    "status_3xx": 0,
    "status_4xx": 0,
    "status_5xx": 0
  },
  {
    "framework": "aspnet-minimal-aot",
    "language": "C#",
    "rps": 488293,
    "avg_latency": "1.02ms",
    "p99_latency": "11.60ms",
    "cpu": "3539.1%",
    "memory": "842.5MiB",
    "connections": 512,
    "threads": 64,
    "duration": "5s",
    "pipeline": 1,
    "bandwidth": "79.60MB/s",
    "input_bw": "37.72MB/s",
    "reconnects": 244136,
    "status_2xx": 2441469,
    "status_3xx": 0,
    "status_4xx": 0,
    "status_5xx": 0
  },
  {
    "framework": "aspnet-minimal-iouring",
    "language": "C#",
    "rps": 463902,
    "avg_latency": "1.09ms",
    "p99_latency": "11.60ms",
    "cpu": "2581.8%",
    "memory": "130MiB",
    "connections": 512,
    "threads": 64,
    "duration": "5s",
    "pipeline": 1,
    "bandwidth": "76.95MB/s",
    "reconnects": 231947,
    "status_2xx": 2319511,
    "status_3xx": 0,
    "status_4xx": 0,
    "status_5xx": 0
  },
  {
    "framework": "aspnet-mvc",
    "language": "C#",
    "rps": 401720,
    "avg_latency": "1.25ms",
    "p99_latency": "13.10ms",
    "cpu": "3901.2%",
    "memory": "171.5MiB",
    "connections": 512,
    "threads": 64,
    "duration": "5s",
    "pipeline": 1,
    "bandwidth": "63.96MB/s",
    "input_bw": "31.03MB/s",
    "reconnects": 200851,
    "status_2xx": 2008604,
    "status_3xx": 0,
    "status_4xx": 0,
    "status_5xx": 0
  },
  {
    "framework": "bjoern",
    "language": "Python",
    "rps": 13759,
    "avg_latency": "37.24ms",
    "p99_latency": "42.40ms",
    "cpu": "94.4%",
    "memory": "150MiB",
    "connections": 512,
    "threads": 64,
    "duration": "5s",
    "pipeline": 1,
    "bandwidth": "1.63MB/s",
    "input_bw": "1.06MB/s",
    "reconnects": 6656,
    "status_2xx": 68799,
    "status_3xx": 0,
    "status_4xx": 0,
    "status_5xx": 0
  },
  {
    "framework": "bottle",
    "language": "Python",
    "rps": 152370,
    "avg_latency": "3.25ms",
    "p99_latency": "3.75ms",
    "cpu": "5655.5%",
    "memory": "2.5GiB",
    "connections": 512,
    "threads": 64,
    "duration": "5s",
    "pipeline": 1,
    "bandwidth": "22.52MB/s",
    "input_bw": "11.77MB/s",
    "reconnects": 761849,
    "status_2xx": 761854,
    "status_3xx": 0,
    "status_4xx": 0,
    "status_5xx": 0
  },
  {
    "framework": "caddy",
    "language": "Go",
    "rps": 231461,
    "avg_latency": "2.21ms",
    "p99_latency": "22.30ms",
    "cpu": "3607.8%",
    "memory": "75MiB",
    "connections": 512,
    "threads": 64,
    "duration": "5s",
    "pipeline": 1,
    "bandwidth": "25.82MB/s",
    "reconnects": 115716,
    "status_2xx": 1157305,
    "status_3xx": 0,
    "status_4xx": 0,
    "status_5xx": 0
  },
  {
    "framework": "elysia",
    "language": "TS",
    "rps": 1279234,
    "avg_latency": "391us",
    "p99_latency": "3.76ms",
    "cpu": "5212.1%",
    "memory": "1.1GiB",
    "connections": 512,
    "threads": 64,
    "duration": "5s",
    "pipeline": 1,
    "bandwidth": "161.02MB/s",
    "reconnects": 639642,
    "status_2xx": 6396171,
    "status_3xx": 0,
    "status_4xx": 0,
    "status_5xx": 0
  },
  {
    "framework": "envoy",
    "language": "C++",
    "rps": 551833,
    "avg_latency": "918us",
    "p99_latency": "4.15ms",
    "cpu": "5683.7%",
    "memory": "105MiB",
    "connections": 512,
    "threads": 64,
    "duration": "5s",
    "pipeline": 1,
    "bandwidth": "62.66MB/s",
    "reconnects": 279074,
    "status_2xx": 2759167,
    "status_3xx": 0,
    "status_4xx": 0,
    "status_5xx": 0
  },
  {
    "framework": "fastapi",
    "language": "Python",
    "rps": 129440,
    "avg_latency": "3.95ms",
    "p99_latency": "7.64ms",
    "cpu": "6498.1%",
    "memory": "5.1GiB",
    "connections": 512,
    "threads": 64,
    "duration": "5s",
    "pipeline": 1,
    "bandwidth": "21.47MB/s",
    "reconnects": 64724,
    "status_2xx": 647202,
    "status_3xx": 0,
    "status_4xx": 0,
    "status_5xx": 0
  },
  {
    "framework": "fastpysgi-asgi",
    "language": "Python",
    "rps": 608712,
    "avg_latency": "832us",
    "p99_latency": "2.77ms",
    "cpu": "6093.1%",
    "memory": "360.6MiB",
    "connections": 512,
    "threads": 64,
    "duration": "5s",
    "pipeline": 1,
    "bandwidth": "95.76MB/s",
    "input_bw": "47.02MB/s",
    "reconnects": 304342,
    "status_2xx": 3043562,
    "status_3xx": 0,
    "status_4xx": 0,
    "status_5xx": 0
  },
  {
    "framework": "fastpysgi-wsgi",
    "language": "Python",
    "rps": 1067572,
    "avg_latency": "469us",
    "p99_latency": "4.24ms",
    "cpu": "6079.3%",
    "memory": "269.5MiB",
    "connections": 512,
    "threads": 64,
    "duration": "5s",
    "pipeline": 1,
    "bandwidth": "167.95MB/s",
    "input_bw": "82.47MB/s",
    "reconnects": 533800,
    "status_2xx": 5337861,
    "status_3xx": 0,
    "status_4xx": 0,
    "status_5xx": 0
  },
  {
    "framework": "flask",
    "language": "Python",
    "rps": 113993,
    "avg_latency": "4.29ms",
    "p99_latency": "5.28ms",
    "cpu": "6042.0%",
    "memory": "3.2GiB",
    "connections": 512,
    "threads": 64,
    "duration": "5s",
    "pipeline": 1,
    "bandwidth": "16.63MB/s",
    "reconnects": 569982,
    "status_2xx": 569968,
    "status_3xx": 0,
    "status_4xx": 0,
    "status_5xx": 0
  },
  {
    "framework": "Fletch",
    "language": "Dart",
    "rps": 459714,
    "avg_latency": "1.07ms",
    "p99_latency": "5.02ms",
    "cpu": "5650.8%",
    "memory": "3.2GiB",
    "connections": 512,
    "threads": 64,
    "duration": "5s",
    "pipeline": 1,
    "bandwidth": "85.47MB/s",
    "input_bw": "35.51MB/s",
    "reconnects": 229855,
    "status_2xx": 2298571,
    "status_3xx": 0,
    "status_4xx": 0,
    "status_5xx": 0
  },
  {
    "framework": "frankenphp-trueasync",
    "language": "PHP",
    "rps": 150425,
    "avg_latency": "3.40ms",
    "p99_latency": "17.10ms",
    "cpu": "2900.4%",
    "memory": "480.4MiB",
    "connections": 512,
    "threads": 64,
    "duration": "5s",
    "pipeline": 1,
    "bandwidth": "16.92MB/s",
    "input_bw": "11.62MB/s",
    "reconnects": 75190,
    "status_2xx": 752126,
    "status_3xx": 0,
    "status_4xx": 0,
    "status_5xx": 0
  },
  {
    "framework": "genhttp",
    "language": "C#",
    "rps": 874280,
    "avg_latency": "575us",
    "p99_latency": "7.95ms",
    "cpu": "6056.0%",
    "memory": "319MiB",
    "connections": 512,
    "threads": 64,
    "duration": "5s",
    "pipeline": 1,
    "bandwidth": "119.20MB/s",
    "reconnects": 437328,
    "status_2xx": 4371403,
    "status_3xx": 0,
    "status_4xx": 0,
    "status_5xx": 0
  },
  {
    "framework": "go-fasthttp",
    "language": "Go",
    "rps": 201821,
    "avg_latency": "2.53ms",
    "p99_latency": "59.80ms",
    "cpu": "2533.8%",
    "memory": "77.3MiB",
    "connections": 512,
    "threads": 64,
    "duration": "5s",
    "pipeline": 1,
    "bandwidth": "23.86MB/s",
    "input_bw": "15.59MB/s",
    "reconnects": 100897,
    "status_2xx": 1009107,
    "status_3xx": 0,
    "status_4xx": 0,
    "status_5xx": 0
  },
  {
    "framework": "h2o",
    "language": "C",
    "rps": 2002574,
    "avg_latency": "243us",
    "p99_latency": "2.75ms",
    "cpu": "5708.5%",
    "memory": "54.1MiB",
    "connections": 512,
    "threads": 64,
    "duration": "5s",
    "pipeline": 1,
    "bandwidth": "196.64MB/s",
    "input_bw": "154.69MB/s",
    "reconnects": 1001281,
    "status_2xx": 10012870,
    "status_3xx": 0,
    "status_4xx": 0,
    "status_5xx": 0
  },
  {
    "framework": "h2o-mruby",
    "language": "Ruby",
    "rps": 832217,
    "avg_latency": "599us",
    "p99_latency": "2.46ms",
    "cpu": "6059.9%",
    "memory": "145MiB",
    "connections": 512,
    "threads": 64,
    "duration": "5s",
    "pipeline": 1,
    "bandwidth": "125.33MB/s",
    "input_bw": "64.29MB/s",
    "reconnects": 415918,
    "status_2xx": 4161088,
    "status_3xx": 0,
    "status_4xx": 0,
    "status_5xx": 0
  },
  {
    "framework": "helidon-production",
    "language": "Java",
    "rps": 587778,
    "avg_latency": "862us",
    "p99_latency": "7.93ms",
    "cpu": "5147.1%",
    "memory": "3.0GiB",
    "connections": 512,
    "threads": 64,
    "duration": "5s",
    "pipeline": 1,
    "bandwidth": "80.69MB/s",
    "input_bw": "45.40MB/s",
    "reconnects": 293892,
    "status_2xx": 2938890,
    "status_3xx": 0,
    "status_4xx": 0,
    "status_5xx": 0
  },
  {
    "framework": "helidon-tuned",
    "language": "Java",
    "rps": 577823,
    "avg_latency": "878us",
    "p99_latency": "7.89ms",
    "cpu": "4862.2%",
    "memory": "3.8GiB",
    "connections": 512,
    "threads": 64,
    "duration": "5s",
    "pipeline": 1,
    "bandwidth": "66.10MB/s",
    "input_bw": "44.64MB/s",
    "reconnects": 288910,
    "status_2xx": 2889119,
    "status_3xx": 0,
    "status_4xx": 0,
    "status_5xx": 0
  },
  {
    "framework": "hono-bun",
    "language": "TS",
    "rps": 941234,
    "avg_latency": "535us",
    "p99_latency": "4.79ms",
    "cpu": "5240.0%",
    "memory": "1.5GiB",
    "connections": 512,
    "threads": 64,
    "duration": "5s",
    "pipeline": 1,
    "bandwidth": "108.58MB/s",
    "input_bw": "72.71MB/s",
    "reconnects": 470627,
    "status_2xx": 4706171,
    "status_3xx": 0,
    "status_4xx": 0,
    "status_5xx": 0
  },
  {
    "framework": "humming-bird",
    "language": "Swift",
    "rps": 127675,
    "avg_latency": "2.42ms",
    "p99_latency": "20.60ms",
    "cpu": "2216.6%",
    "memory": "42.5MiB",
    "connections": 512,
    "threads": 64,
    "duration": "5s",
    "pipeline": 1,
    "bandwidth": "15.09MB/s",
    "input_bw": "9.86MB/s",
    "reconnects": 63836,
    "status_2xx": 638379,
    "status_3xx": 0,
    "status_4xx": 0,
    "status_5xx": 0
  },
  {
    "framework": "hyper",
    "language": "Rust",
    "rps": 2021689,
    "avg_latency": "240us",
    "p99_latency": "1.03ms",
    "cpu": "5748.4%",
    "memory": "80.5MiB",
    "connections": 512,
    "threads": 64,
    "duration": "5s",
    "pipeline": 1,
    "bandwidth": "227.40MB/s",
    "input_bw": "156.17MB/s",
    "reconnects": 1010827,
    "status_2xx": 10108447,
    "status_3xx": 0,
    "status_4xx": 0,
    "status_5xx": 0
  },
  {
    "framework": "hyperf",
    "language": "PHP",
    "rps": 279032,
    "avg_latency": "1.83ms",
    "p99_latency": "3.05ms",
    "cpu": "3306.0%",
    "memory": "1.8GiB",
    "connections": 512,
    "threads": 64,
    "duration": "5s",
    "pipeline": 1,
    "bandwidth": "41.77MB/s",
    "reconnects": 139516,
    "status_2xx": 1395163,
    "status_3xx": 0,
    "status_4xx": 0,
    "status_5xx": 0
  },
  {
    "framework": "libreactorng",
    "language": "C",
    "rps": 2331986,
    "avg_latency": "204us",
    "p99_latency": "1.15ms",
    "cpu": "5259.4%",
    "memory": "91MiB",
    "connections": 512,
    "threads": 64,
    "duration": "5s",
    "pipeline": 1,
    "bandwidth": "253.42MB/s",
    "input_bw": "180.14MB/s",
    "reconnects": 1165994,
    "status_2xx": 11659931,
    "status_3xx": 0,
    "status_4xx": 0,
    "status_5xx": 0
  },
  {
    "framework": "lute",
    "language": "Luau",
    "rps": 1839624,
    "avg_latency": "265us",
    "p99_latency": "1.17ms",
    "cpu": "5366.9%",
    "memory": "107MiB",
    "connections": 512,
    "threads": 64,
    "duration": "5s",
    "pipeline": 1,
    "bandwidth": "210.45MB/s",
    "input_bw": "142.11MB/s",
    "reconnects": 919840,
    "status_2xx": 9198123,
    "status_3xx": 0,
    "status_4xx": 0,
    "status_5xx": 0
  },
  {
    "framework": "mark",
    "language": "PHP",
    "rps": 1825079,
    "avg_latency": "268us",
    "p99_latency": "2.08ms",
    "cpu": "6092.5%",
    "memory": "124MiB",
    "connections": 512,
    "threads": 64,
    "duration": "5s",
    "pipeline": 1,
    "bandwidth": "154.86MB/s",
    "reconnects": 912540,
    "status_2xx": 9125397,
    "status_3xx": 0,
    "status_4xx": 0,
    "status_5xx": 0
  },
  {
    "framework": "may-minihttp",
    "language": "Rust",
    "rps": 755586,
    "avg_latency": "670us",
    "p99_latency": "6.48ms",
    "cpu": "2033.2%",
    "memory": "116.2MiB",
    "connections": 512,
    "threads": 64,
    "duration": "5s",
    "pipeline": 1,
    "bandwidth": "47.54MB/s",
    "input_bw": "58.37MB/s",
    "reconnects": 377794,
    "status_2xx": 3777930,
    "status_3xx": 0,
    "status_4xx": 0,
    "status_5xx": 0
  },
  {
    "framework": "nginx",
    "language": "C",
    "rps": 2062243,
    "avg_latency": "234us",
    "p99_latency": "2.20ms",
    "cpu": "5945.5%",
    "memory": "3.5GiB",
    "connections": 512,
    "threads": 64,
    "duration": "5s",
    "pipeline": 1,
    "bandwidth": "279.20MB/s",
    "input_bw": "159.30MB/s",
    "reconnects": 1031117,
    "status_2xx": 10311216,
    "status_3xx": 0,
    "status_4xx": 0,
    "status_5xx": 0
  },
  {
    "framework": "ngx-php",
    "language": "PHP",
    "rps": 724148,
    "avg_latency": "604us",
    "p99_latency": "9.69ms",
    "cpu": "3338.7%",
    "memory": "4.4GiB",
    "connections": 512,
    "threads": 64,
    "duration": "5s",
    "pipeline": 1,
    "bandwidth": "98.03MB/s",
    "input_bw": "55.94MB/s",
    "reconnects": 1006375,
    "status_2xx": 3620740,
    "status_3xx": 0,
    "status_4xx": 0,
    "status_5xx": 0
  },
  {
    "framework": "php-fpm",
    "language": "PHP",
    "rps": 266984,
    "avg_latency": "1.91ms",
    "p99_latency": "6.15ms",
    "cpu": "6435.4%",
    "memory": "3.8GiB",
    "connections": 512,
    "threads": 64,
    "duration": "5s",
    "pipeline": 1,
    "bandwidth": "50.91MB/s",
    "input_bw": "20.62MB/s",
    "reconnects": 133485,
    "status_2xx": 1334923,
    "status_3xx": 0,
    "status_4xx": 0,
    "status_5xx": 0
  },
  {
    "framework": "pingora",
    "language": "Rust",
    "rps": 513912,
    "avg_latency": "988us",
    "p99_latency": "7.95ms",
    "cpu": "1956.2%",
    "memory": "212MiB",
    "connections": 512,
    "threads": 64,
    "duration": "5s",
    "pipeline": 1,
    "bandwidth": "61.74MB/s",
    "reconnects": 256907,
    "status_2xx": 2569562,
    "status_3xx": 0,
    "status_4xx": 0,
    "status_5xx": 0
  },
  {
    "framework": "pyronova",
    "language": "Python",
    "rps": 265804,
    "avg_latency": "1.92ms",
    "p99_latency": "5.77ms",
    "cpu": "2374.3%",
    "memory": "1.1GiB",
    "connections": 512,
    "threads": 64,
    "duration": "5s",
    "pipeline": 1,
    "bandwidth": "32.18MB/s",
    "input_bw": "20.53MB/s",
    "reconnects": 132898,
    "status_2xx": 1329021,
    "status_3xx": 0,
    "status_4xx": 0,
    "status_5xx": 0
  },
  {
    "framework": "quarkus-jvm",
    "language": "Java",
    "rps": 564915,
    "avg_latency": "898us",
    "p99_latency": "8.88ms",
    "cpu": "2948.1%",
    "memory": "1.3GiB",
    "connections": 512,
    "threads": 64,
    "duration": "5s",
    "pipeline": 1,
    "bandwidth": "54.39MB/s",
    "input_bw": "43.64MB/s",
    "reconnects": 282451,
    "status_2xx": 2824575,
    "status_3xx": 0,
    "status_4xx": 0,
    "status_5xx": 0
  },
  {
    "framework": "rage",
    "language": "Ruby",
    "rps": 54318,
    "avg_latency": "9.39ms",
    "p99_latency": "64.60ms",
    "cpu": "4674.3%",
    "memory": "4.7GiB",
    "connections": 512,
    "threads": 64,
    "duration": "5s",
    "pipeline": 1,
    "bandwidth": "7.82MB/s",
    "input_bw": "4.20MB/s",
    "reconnects": 27006,
    "status_2xx": 271590,
    "status_3xx": 0,
    "status_4xx": 0,
    "status_5xx": 0
  },
  {
    "framework": "rails",
    "language": "Ruby",
    "rps": 28552,
    "avg_latency": "17.90ms",
    "p99_latency": "83.80ms",
    "cpu": "4991.0%",
    "memory": "5.8GiB",
    "connections": 512,
    "threads": 64,
    "duration": "5s",
    "pipeline": 1,
    "bandwidth": "5.80MB/s",
    "input_bw": "2.21MB/s",
    "reconnects": 14161,
    "status_2xx": 142761,
    "status_3xx": 0,
    "status_4xx": 0,
    "status_5xx": 0
  },
  {
    "framework": "ring-http-exchange",
    "language": "Clojure",
    "rps": 783753,
    "avg_latency": "644us",
    "p99_latency": "5.93ms",
    "cpu": "5383.0%",
    "memory": "1.3GiB",
    "connections": 512,
    "threads": 64,
    "duration": "5s",
    "pipeline": 1,
    "bandwidth": "97.14MB/s",
    "reconnects": 391866,
    "status_2xx": 3918765,
    "status_3xx": 0,
    "status_4xx": 0,
    "status_5xx": 0
  },
  {
    "framework": "ringzero",
    "language": "C",
    "rps": 1422422,
    "avg_latency": "344us",
    "p99_latency": "3.02ms",
    "cpu": "2629.8%",
    "memory": "4.1GiB",
    "connections": 512,
    "threads": 64,
    "duration": "5s",
    "pipeline": 1,
    "bandwidth": "113.85MB/s",
    "input_bw": "109.88MB/s",
    "reconnects": 711229,
    "status_2xx": 7112110,
    "status_3xx": 0,
    "status_4xx": 147,
    "status_5xx": 0
  },
  {
    "framework": "robyn",
    "language": "Python",
    "rps": 284472,
    "avg_latency": "1.75ms",
    "p99_latency": "14.00ms",
    "cpu": "5854.5%",
    "memory": "894MiB",
    "connections": 512,
    "threads": 64,
    "duration": "5s",
    "pipeline": 1,
    "bandwidth": "32.00MB/s",
    "input_bw": "21.97MB/s",
    "reconnects": 142300,
    "status_2xx": 1422363,
    "status_3xx": 0,
    "status_4xx": 0,
    "status_5xx": 0
  },
  {
    "framework": "roda",
    "language": "Ruby",
    "rps": 30282,
    "avg_latency": "16.88ms",
    "p99_latency": "88.00ms",
    "cpu": "4333.7%",
    "memory": "5.3GiB",
    "connections": 512,
    "threads": 64,
    "duration": "5s",
    "pipeline": 1,
    "bandwidth": "2.31MB/s",
    "input_bw": "2.34MB/s",
    "reconnects": 14995,
    "status_2xx": 151412,
    "status_3xx": 0,
    "status_4xx": 0,
    "status_5xx": 0
  },
  {
    "framework": "rust-epoll",
    "language": "Rust",
    "rps": 2502919,
    "avg_latency": "187us",
    "p99_latency": "652us",
    "cpu": "5276.9%",
    "memory": "78.6MiB",
    "connections": 512,
    "threads": 64,
    "duration": "5s",
    "pipeline": 1,
    "bandwidth": "205.20MB/s",
    "input_bw": "193.34MB/s",
    "reconnects": 1251447,
    "status_2xx": 12514598,
    "status_3xx": 0,
    "status_4xx": 0,
    "status_5xx": 0
  },
  {
    "framework": "servicestack",
    "language": "C#",
    "rps": 18651,
    "avg_latency": "27.50ms",
    "p99_latency": "88.40ms",
    "cpu": "1042.8%",
    "memory": "250MiB",
    "connections": 512,
    "threads": 64,
    "duration": "5s",
    "pipeline": 1,
    "bandwidth": "3.75MB/s",
    "input_bw": "1.44MB/s",
    "reconnects": 9214,
    "status_2xx": 93257,
    "status_3xx": 0,
    "status_4xx": 0,
    "status_5xx": 0
  },
  {
    "framework": "sinatra",
    "language": "Ruby",
    "rps": 41034,
    "avg_latency": "12.45ms",
    "p99_latency": "66.00ms",
    "cpu": "4080.0%",
    "memory": "4.2GiB",
    "connections": 512,
    "threads": 64,
    "duration": "5s",
    "pipeline": 1,
    "bandwidth": "3.25MB/s",
    "input_bw": "3.17MB/s",
    "reconnects": 20394,
    "status_2xx": 205174,
    "status_3xx": 0,
    "status_4xx": 0,
    "status_5xx": 0
  },
  {
    "framework": "SlimeWeb",
    "language": "Python",
    "rps": 72654,
    "avg_latency": "6.12ms",
    "p99_latency": "16.70ms",
    "cpu": "1311.5%",
    "memory": "131MiB",
    "connections": 512,
    "threads": 64,
    "duration": "5s",
    "pipeline": 1,
    "bandwidth": "8.52MB/s",
    "reconnects": 36257,
    "status_2xx": 363270,
    "status_3xx": 0,
    "status_4xx": 0,
    "status_5xx": 0
  },
  {
    "framework": "spring-boot",
    "language": "Java",
    "rps": 228052,
    "avg_latency": "2.02ms",
    "p99_latency": "4.01ms",
    "cpu": "1879.4%",
    "memory": "1.4GiB",
    "connections": 512,
    "threads": 64,
    "duration": "5s",
    "pipeline": 1,
    "bandwidth": "25.00MB/s",
    "input_bw": "17.62MB/s",
    "reconnects": 113919,
    "status_2xx": 1140264,
    "status_3xx": 0,
    "status_4xx": 0,
    "status_5xx": 0
  },
  {
    "framework": "swerver",
    "language": "Zig",
    "rps": 2073679,
    "avg_latency": "222us",
    "p99_latency": "783us",
    "cpu": "6404.5%",
    "memory": "1.6GiB",
    "connections": 512,
    "threads": 64,
    "duration": "5s",
    "pipeline": 1,
    "bandwidth": "203.64MB/s",
    "input_bw": "160.19MB/s",
    "reconnects": 1275142,
    "status_2xx": 10368397,
    "status_3xx": 0,
    "status_4xx": 0,
    "status_5xx": 0
  },
  {
    "framework": "Swoole",
    "language": "PHP",
    "rps": 1511351,
    "avg_latency": "327us",
    "p99_latency": "3.59ms",
    "cpu": "6059.2%",
    "memory": "215.2MiB",
    "connections": 512,
    "threads": 64,
    "duration": "5s",
    "pipeline": 1,
    "bandwidth": "223.35MB/s",
    "input_bw": "116.75MB/s",
    "reconnects": 755679,
    "status_2xx": 7556756,
    "status_3xx": 0,
    "status_4xx": 0,
    "status_5xx": 0
  },
  {
    "framework": "traefik",
    "language": "Go",
    "rps": 297555,
    "avg_latency": "1.71ms",
    "p99_latency": "16.70ms",
    "cpu": "4713.0%",
    "memory": "156MiB",
    "connections": 512,
    "threads": 64,
    "duration": "5s",
    "pipeline": 1,
    "bandwidth": "28.93MB/s",
    "reconnects": 148776,
    "status_2xx": 1487778,
    "status_3xx": 0,
    "status_4xx": 0,
    "status_5xx": 0
  },
  {
    "framework": "uvicorn",
    "language": "Python",
    "rps": 570633,
    "avg_latency": "886us",
    "p99_latency": "1.87ms",
    "cpu": "6400.2%",
    "memory": "4.9GiB",
    "connections": 512,
    "threads": 64,
    "duration": "5s",
    "pipeline": 1,
    "bandwidth": "83.23MB/s",
    "reconnects": 285311,
    "status_2xx": 2853166,
    "status_3xx": 0,
    "status_4xx": 0,
    "status_5xx": 0
  },
  {
    "framework": "workerman",
    "language": "PHP",
    "rps": 1967016,
    "avg_latency": "246us",
    "p99_latency": "1.97ms",
    "cpu": "5577.4%",
    "memory": "193MiB",
    "connections": 512,
    "threads": 64,
    "duration": "5s",
    "pipeline": 1,
    "bandwidth": "166.89MB/s",
    "reconnects": 983492,
    "status_2xx": 9835082,
    "status_3xx": 0,
    "status_4xx": 0,
    "status_5xx": 0
  }
]